lsclib/__init__.py
lsclib/coordinate_transformations.py
lsclib/external_equations.py
lsclib/lsc_calcs.py
lsclib/lsc_classes.py
lsclib/lsc_external_equations.py
lsclib/particle_calcs.py
lsclib/rotations.py
lsclib/run.py
lsclib/xls_read_interpolate.py
lsclib/data/absorption_matrix.csv
lsclib/data/absorption_particle.csv
lsclib/data/emission_AM1.5.csv
lsclib/data/emission_particle.csv
lsclib/data/emission_source.csv
lsclib/data/eqe_pv.csv
lsclib/data/iqe_pv.csv
lsclib-0.1.1.dist-info/LICENSE
lsclib-0.1.1.dist-info/METADATA
lsclib-0.1.1.dist-info/WHEEL
lsclib-0.1.1.dist-info/top_level.txt
lsclib-0.1.1.dist-info/RECORD
